greptime/__init__.py
greptime-0.0.4.dist-info/METADATA
greptime-0.0.4.dist-info/WHEEL
greptime-0.0.4.dist-info/top_level.txt
greptime-0.0.4.dist-info/RECORD
