Metadata-Version: 2.1
Name: greptime
Version: 0.0.4
Summary: A mock test library for greptimedb's scripting feature
Home-page: https://github.com/GreptimeTeam/greptime_py_mock
Author: discord9
Author-email: zglzy29yzdk@gmail.com
License: Apache License 2.0
Project-URL: Bug Tracker, https://github.com/GreptimeTeam/greptime_py_mock/issues
Requires-Python: >=3.6
Requires-Dist: numpy
